server_dist/__init__.py
server_dist/server.py
server_dist/common/__init__.py
server_dist/common/decos.py
server_dist/common/descryptors.py
server_dist/common/errors.py
server_dist/common/metaclasses.py
server_dist/common/utils.py
server_dist/common/variables.py
server_dist/logs/__init__.py
server_dist/logs/config_client_log.py
server_dist/logs/config_server_log.py
server_dist/server/__init__.py
server_dist/server/add_user.py
server_dist/server/config_window.py
server_dist/server/core.py
server_dist/server/database.py
server_dist/server/main_window.py
server_dist/server/remove_user.py
server_dist/server/stat_window.py
server_dist/unit_tests/__init__.py
aaznutii_messenger_server-0.0.1.dist-info/METADATA
aaznutii_messenger_server-0.0.1.dist-info/WHEEL
aaznutii_messenger_server-0.0.1.dist-info/top_level.txt
aaznutii_messenger_server-0.0.1.dist-info/RECORD
