Metadata-Version: 2.1
Name: aaznutii-messenger-server
Version: 0.0.1
Summary: Messenger Server
Home-page: UNKNOWN
Author: Arjanov Alexey
Author-email: aaznutii@mail.ru
License: UNKNOWN
Platform: UNKNOWN
Requires-Dist: PyQt5
Requires-Dist: sqlalchemy
Requires-Dist: pycryptodome
Requires-Dist: pycryptodomex
